[
  [{"id": 1, "anime": "Full Metal Panic! IV Episode 12", "name": "Even...if (English Ver.) by Tamaru Yamada", "video": "https://naedist.animemusicquiz.com/er48rr.webm", "mp3": "https://naedist.animemusicquiz.com/teevc2.mp3" },                                                             {"id": 1, "anime": "Full Metal Panic! IV Episode 12", "name": "tomorrow by Mikuni Shimokawa", "video": "https://naedist.animemusicquiz.com/4y71un.webm", "mp3": "https://naedist.animemusicquiz.com/4bhmw0.mp3" },                                                                                                  {"id": 1, "anime": "Full Metal Panic! IV Episode 12", "name": "Karenai Hana by Mikuni Shimokawa", "video": "https://naedist.animemusicquiz.com/yje5nu.webm", "mp3": "https://naedist.animemusicquiz.com/xzl015.mp3" }],
  [{"id": 2, "anime": "Clannad After Story Episode 22", "name": "Toki o Kizamu Uta by Lia", "video": "https://naedist.animemusicquiz.com/1dhitq.webm", "mp3": "https://naedist.animemusicquiz.com/689oww.mp3" },                                                                               {"id": 2, "anime": "Clannad After Story Episode 22", "name": "TORCH by Lia", "video": "https://naedist.animemusicquiz.com/st04yj.webm", "mp3": "https://naedist.animemusicquiz.com/meq0zy.mp3" },                                                                                                                   {"id": 2, "anime": "Clannad After Story Episode 22", "name": "Chiisana Tenohira by riya", "video": "https://naedist.animemusicquiz.com/nft2jx.webm", "mp3": "https://naedist.animemusicquiz.com/p2rie0.mp3" }],
  [{"id": 3, "anime": "Idol Bouei-tai Hummingbird Episode 3", "name": "MY BLUE PARADISE by Fumie Kusachi", "video": "https://naedist.animemusicquiz.com/fwgixi.webm", "mp3": "https://naedist.animemusicquiz.com/uk7zpa.mp3" },                                                                {"id": 3, "anime": "Idol Bouei-tai Hummingbird Episode 3", "name": "Shitsuren Zenya by Hummingbird", "video": "https://naedist.animemusicquiz.com/69lgd7.webm", "mp3": "https://naedist.animemusicquiz.com/4fimi2.mp3" },                                                                                           {"id": 3, "anime": "Idol Bouei-tai Hummingbird Episode 3", "name": "Ii Ko de wa Irarenai by Sakiko Tamagawa & Yuri Amano", "video": "https://naedist.animemusicquiz.com/eqbfz9.webm", "mp3": "https://naedist.animemusicquiz.com/ff2bb0.mp3" }],
  [{"id": 4, "anime": "Spy×Family Episode 5", "name": "Mixed Nuts by Official HIGE DANdism", "video": "https://naedist.animemusicquiz.com/pxds9u.webm", "mp3": "https://naedist.animemusicquiz.com/jpl7nw.mp3" },                                                                              {"id": 4, "anime": "Spy×Family Episode 5", "name": "Kigeki by Gen Hoshino", "video": "https://naedist.animemusicquiz.com/rx87qr.webm", "mp3": "https://naedist.animemusicquiz.com/y7m7o4.mp3" },                                                                                                                    {"id": 4, "anime": "Spy×Family Episode 5", "name": "TBD by (K)NoW_NAME:Ayaka Tachibana", "video": "https://naedist.animemusicquiz.com/bsrhtr.webm", "mp3": "https://naedist.animemusicquiz.com/axpg2h.mp3" }],
  [{"id": 5, "anime": "Boku no Kokoro no Yabai Yatsu 2nd Season Episode 13", "name": "Boku wa... by Atarayo", "video": "https://naedist.animemusicquiz.com/nzt5qc.webm", "mp3": "https://naedist.animemusicquiz.com/ln7q5x.mp3" },                                                             {"id": 5, "anime": "Boku no Kokoro no Yabai Yatsu 2nd Season Episode 13", "name": "Shayou by Yorushika", "video": "https://naedist.animemusicquiz.com/4um6um.webm", "mp3": "https://naedist.animemusicquiz.com/5wfk4j.mp3" },                                                                                       {"id": 5, "anime": "Boku no Kokoro no Yabai Yatsu 2nd Season Episode 13", "name": "Koishiteru Jibun Sura Aiserunda by Kohana Lam", "video": "https://files.catbox.moe/zr6v8r.mp4", "mp3": "https://files.catbox.moe/htviij.mp3" }],
  [{"id": 6, "anime": "Bocchi the Rock! Re:", "name": "Tsukinami ni Kagayake by Kessoku Band", "video": "https://naedist.animemusicquiz.com/z9mfek.webm", "mp3": "https://naedist.animemusicquiz.com/72mei3.mp3" },                                                                            {"id": 6, "anime": "Bocchi the Rock! Re:", "name": "Ima, Boku, Underground kara by Kessoku Band", "video": "https://naedist.animemusicquiz.com/iqf4w7.webm", "mp3": "https://naedist.animemusicquiz.com/ayjmyp.mp3" },                                                                                              {"id": 6, "anime": "Bocchi the Rock! Re:", "name": "Guitar to Kodoku to Aoi Hoshi by Kessoku Band", "video": "https://naedist.animemusicquiz.com/bocvt9.webm", "mp3": "https://naedist.animemusicquiz.com/habzrd.mp3" }],
  [{"id": 7, "anime": "Grisaia no Kajitsu Episode 6", "name": "Rakuen no Tsubasa by Maon Kurosaki", "video": "https://naedist.animemusicquiz.com/qapt9w.webm", "mp3": "https://naedist.animemusicquiz.com/nyxufc.mp3" },                                                                       {"id": 7, "anime": "Grisaia no Kajitsu Episode 6", "name": "Anata no Aishita Sekai by Yoshino Nanjo", "video": "https://naedist.animemusicquiz.com/y0t7u0.webm", "mp3": "https://naedist.animemusicquiz.com/qgy3ux.mp3" },                                                                                          {"id": 7, "anime": "Grisaia no Kajitsu Episode 6", "name": "Holograph by eufonius", "video": "https://naedist.animemusicquiz.com/qvrwxj.webm", "mp3": "https://naedist.animemusicquiz.com/0w34ql.mp3" }],
  [{"id": 8, "anime": "Break Blade Episode 7", "name": "Junction heart by Sayaka Sasaki", "video": "https://naedist.animemusicquiz.com/has32h.webm", "mp3": "https://naedist.animemusicquiz.com/9amk1r.mp3" },                                                                                 {"id": 8, "anime": "Break Blade Episode 7", "name": "Itoshiki Aragai yo, Michibike Hikari e by Aira Yuuki", "video": "https://naedist.animemusicquiz.com/drqh2t.webm", "mp3": "https://naedist.animemusicquiz.com/8mqsrb.mp3" },                                                                                    {"id": 8, "anime": "Break Blade Episode 7", "name": "Omoi by KOKIA", "video": "https://naedist.animemusicquiz.com/rsnh3f.webm", "mp3": "https://naedist.animemusicquiz.com/cronjz.mp3" }],
  [{"id": 9, "anime": "Koukaku Kidoutai: Stand Alone Complex 2nd GIG Episode 4", "name": "rise by Origa", "video": "https://naedist.animemusicquiz.com/6q989a.webm", "mp3": "https://naedist.animemusicquiz.com/worf92.mp3" },                                                                 {"id": 9, "anime": "Koukaku Kidoutai: Stand Alone Complex 2nd GIG Episode 4", "name": "living inside the shell by Steve Conte", "video": "https://naedist.animemusicquiz.com/9mmntv.webm", "mp3": "https://naedist.animemusicquiz.com/xltmu3.mp3" },                                                                {"id": 9, "anime": "Koukaku Kidoutai: Stand Alone Complex 2nd GIG Episode 4", "name": "Cyber Bird by Gabriela Robin", "video": "https://naedist.animemusicquiz.com/h66nzh.webm", "mp3": "https://naedist.animemusicquiz.com/xek6wy.mp3" }],
  [{"id": 10, "anime": "Ore dake Level Up na Ken Season 2: Arise from the Shadow Episode 11", "name": "ReawakeR by LiSA feat. Felix of Stray Kids", "video": "https://naedist.animemusicquiz.com/zbxil2.webm", "mp3": "https://naedist.animemusicquiz.com/450vy1.mp3" },                       {"id": 10, "anime": "Ore dake Level Up na Ken Season 2: Arise from the Shadow Episode 11", "name": "UN-APEX by TK from Ling Tosite Sigure", "video": "https://naedist.animemusicquiz.com/0v56kt.webm", "mp3": "https://naedist.animemusicquiz.com/2r8z0c.mp3" },                                                    {"id": 10, "anime": "Ore dake Level Up na Ken Season 2: Arise from the Shadow Episode 11", "name": "DARK ARIA by XAI", "video": "https://naedist.animemusicquiz.com/zzghat.webm", "mp3": "https://files.catbox.moe/2jfnt8.mp3" }],
  [{"id": 11, "anime": "World Dai Star Episode 3", "name": "Wanna Be Star! by Manaka Iwami, Ikumi Hasegawa, Sally Amaki, Maria Naganawa, Naomi Oozora, Rico Sasaki", "video": "https://naedist.animemusicquiz.com/xzx2gr.webm", "mp3": "https://naedist.animemusicquiz.com/kc20t7.mp3" },      {"id": 11, "anime": "World Dai Star Episode 3", "name": "Two Of Us by Manaka Iwami & Ikumi Hasegawa", "video": "https://naedist.animemusicquiz.com/6bp6fn.webm", "mp3": "https://naedist.animemusicquiz.com/u4ihyx.mp3" },                                                                                          {"id": 11, "anime": "World Dai Star Episode 3", "name": "Wasurena Uta by Manaka Iwami & Ikumi Hasegawa", "video": "https://naedist.animemusicquiz.com/9phi4c.webm", "mp3": "https://naedist.animemusicquiz.com/wnidff.mp3" }],
  [{"id": 12, "anime": "Natsu e no Tunnel, Sayonara no Deguchi", "name": "Katappo - Acoustic Version by eill", "video": "https://naedist.animemusicquiz.com/zuycpu.webm", "mp3": "https://naedist.animemusicquiz.com/wa5dzd.mp3" },                                                            {"id": 12, "anime": "Natsu e no Tunnel, Sayonara no Deguchi", "name": "Finale. by eill", "video": "https://naedist.animemusicquiz.com/85o7ww.webm", "mp3": "https://naedist.animemusicquiz.com/ku7ggp.mp3" },                                                                                                       {"id": 12, "anime": "Natsu e no Tunnel, Sayonara no Deguchi", "name": "Pre-romance by eill", "video": "https://naedist.animemusicquiz.com/qj87qs.webm", "mp3": "https://naedist.animemusicquiz.com/9bagmg.mp3" }],
  [{"id": 13, "anime": "Aquarion Evol Episode 13", "name": "Kimi no Shinwa ~Aquarion Dai Ni Shou by AKINO with bless4", "video": "https://naedist.animemusicquiz.com/2v5m3g.webm", "mp3": "https://naedist.animemusicquiz.com/dgjobn.mp3" },                                                   {"id": 13, "anime": "Aquarion Evol Episode 13", "name": "Gekkou Symphonia by AKINO&AIKI from bless4", "video": "https://naedist.animemusicquiz.com/aadq7k.webm", "mp3": "https://naedist.animemusicquiz.com/5x8ohy.mp3" },                                                                                          {"id": 13, "anime": "Aquarion Evol Episode 13", "name": "Kouya no Heath by AKINO", "video": "https://naedist.animemusicquiz.com/zsxoh7.webm", "mp3": "https://naedist.animemusicquiz.com/t1c6n8.mp3" }],
  [{"id": 14, "anime": "Kidou Senshi Gundam SEED (Remaster) Episode 45", "name": "Realize by Nami Tamaki", "video": "https://naedist.animemusicquiz.com/ndyipg.webm", "mp3": "https://naedist.animemusicquiz.com/71ydo5.mp3" },                                                                {"id": 14, "anime": "Kidou Senshi Gundam SEED (Remaster) Episode 45", "name": "Distance by FictionJunction", "video": "https://naedist.animemusicquiz.com/oglmrc.webm", "mp3": "https://naedist.animemusicquiz.com/z1d89q.mp3" },                                                                                   {"id": 14, "anime": "Kidou Senshi Gundam SEED (Remaster) Episode 45", "name": "Meteor by T.M.Revolution", "video": "https://files.catbox.moe/rifdte.mp4", "mp3": "https://files.catbox.moe/9arund.mp3" }],
  [{"id": 15, "anime": "One Piece Film: Red", "name": "Shinjidai by Ado", "video": "https://naedist.animemusicquiz.com/uwbwsc.webm", "mp3": "https://naedist.animemusicquiz.com/u7m43n.mp3" },                                                                                                 {"id": 15, "anime": "One Piece Film: Red", "name": "Kaze no Yukue by Ado", "video": "https://naedist.animemusicquiz.com/uo69w4.webm", "mp3": "https://naedist.animemusicquiz.com/lvftb0.mp3" },                                                                                                                     {"id": 15, "anime": "One Piece Film: Red", "name": "Gyakkou by Ado", "video": "https://naedist.animemusicquiz.com/mqyl1y.webm", "mp3": "https://naedist.animemusicquiz.com/3tmlgo.mp3" }],
  [{"id": 16, "anime": "BanG Dream! It's MyGO!!!!! Episode 7", "name": "Hitoshizuku by MyGO!!!!!", "video": "https://naedist.animemusicquiz.com/978mmw.webm", "mp3": "https://naedist.animemusicquiz.com/2rbmmt.mp3" },                                                                        {"id": 16, "anime": "BanG Dream! It's MyGO!!!!! Episode 7", "name": "Shiori by MyGO!!!!!", "video": "https://naedist.animemusicquiz.com/ez3x83.webm", "mp3": "https://naedist.animemusicquiz.com/iz84hz.mp3" },                                                                                                     {"id": 16, "anime": "BanG Dream! It's MyGO!!!!! Episode 7", "name": "Haruhikage MyGO!!!!! ver. by MyGO!!!!!", "video": "https://naedist.animemusicquiz.com/2f3yc0.webm", "mp3": "https://naedist.animemusicquiz.com/j0b0n5.mp3" }],
  [{"id": 17, "anime": "Shuumatsu Nani Shitemasu ka? Isogashii desu ka? Sukutte Moratte Ii desu ka? Episode 12", "name": "DEAREST DROP by Azusa Tadokoro", "video": "https://naedist.animemusicquiz.com/2na05f.webm", "mp3": "https://naedist.animemusicquiz.com/1qv3af.mp3" },                {"id": 17, "anime": "Shuumatsu Nani Shitemasu ka? Isogashii desu ka? Sukutte Moratte Ii desu ka? Episode 12", "name": "Ever be my love by Tamaru Yamada", "video": "https://naedist.animemusicquiz.com/didn9y.webm", "mp3": "https://naedist.animemusicquiz.com/90qefn.mp3" },                                      {"id": 17, "anime": "Shuumatsu Nani Shitemasu ka? Isogashii desu ka? Sukutte Moratte Ii desu ka? Episode 12", "name": "Always in my heart by Tamaru Yamada", "video": "https://naedist.animemusicquiz.com/n3ujpf.webm", "mp3": "https://naedist.animemusicquiz.com/gv9dui.mp3" }],
  [{"id": 18, "anime": "Saenai Heroine no Sodatekata Episode 3", "name": "Kimi-iro Signal by Luna Haruna", "video": "https://naedist.animemusicquiz.com/culbaa.webm", "mp3": "https://naedist.animemusicquiz.com/9oevw6.mp3" },                                                                {"id": 18, "anime": "Saenai Heroine no Sodatekata Episode 3", "name": "Colorful. by Miku Sawai", "video": "https://naedist.animemusicquiz.com/binq9z.webm", "mp3": "https://naedist.animemusicquiz.com/zr7mxy.mp3" },                                                                                               {"id": 18, "anime": "Saenai Heroine no Sodatekata Episode 3", "name": "M♭ by Kiyono Yasuno", "video": "https://naedist.animemusicquiz.com/491jhc.webm", "mp3": "https://naedist.animemusicquiz.com/9jijbv.mp3" }],
  [{"id": 19, "anime": "Toaru Kagaku no Railgun T Episode 15", "name": "final phase by fripSide", "video": "https://naedist.animemusicquiz.com/lkdytn.webm", "mp3": "https://naedist.animemusicquiz.com/sjv4ux.mp3" },                                                                         {"id": 19, "anime": "Toaru Kagaku no Railgun T Episode 15", "name": "nameless story by Kishida Kyoudan &THE Akeboshi Rockets", "video": "https://naedist.animemusicquiz.com/a82xnh.webm", "mp3": "https://naedist.animemusicquiz.com/ujnakw.mp3" },                                                                 {"id": 19, "anime": "Toaru Kagaku no Railgun T Episode 15", "name": "Koko ni Itai by sajou no hana", "video": "https://naedist.animemusicquiz.com/0s9gyp.webm", "mp3": "https://naedist.animemusicquiz.com/kd0my8.mp3" }],
  [{"id": 20, "anime": "Angel Beats! Episode 1", "name": "My Soul,Your Beats! by Lia", "video": "https://naedist.animemusicquiz.com/avvdm5.webm", "mp3": "https://naedist.animemusicquiz.com/ocbvdf.mp3" },                                                                                    {"id": 20, "anime": "Angel Beats! Episode 1", "name": "Brave Song by Aoi Tada", "video": "https://naedist.animemusicquiz.com/2kfutv.webm", "mp3": "https://naedist.animemusicquiz.com/9i3ynu.mp3" },                                                                                                                {"id": 20, "anime": "Angel Beats! Episode 1", "name": "Crow Song by Girls Dead Monster (marina)", "video": "https://naedist.animemusicquiz.com/w8mdut.webm", "mp3": "https://naedist.animemusicquiz.com/xf1zcp.mp3" }],
  [{"id": 21, "anime": "Re:cycle of Penguindrum Part 2: Boku wa Kimi o Aishiteru", "name": "Boku no Sonzai Shoumei by Etsuko Yakushimaru Metro Orchestra", "video": "https://naedist.animemusicquiz.com/kyj3y4.webm", "mp3": "https://naedist.animemusicquiz.com/s2s9ft.mp3" },                {"id": 21, "anime": "Re:cycle of Penguindrum Part 2: Boku wa Kimi o Aishiteru", "name": "Shounen yo Ware ni Kaere by Etsuko Yakushimaru Metro Orchestra", "video": "https://naedist.animemusicquiz.com/vr9zbv.webm", "mp3": "https://naedist.animemusicquiz.com/k9u4gc.mp3" },                                      {"id": 21, "anime": "Re:cycle of Penguindrum Part 2: Boku wa Kimi o Aishiteru", "name": "AFTER '45 by Triple H", "video": "https://naedist.animemusicquiz.com/aigzv1.webm", "mp3": "https://naedist.animemusicquiz.com/rihnvz.mp3" }],
  [{"id": 22, "anime": "White Album 2 Episode 2", "name": "Todokanai Koi '13 by Rena Uehara", "video": "https://naedist.animemusicquiz.com/yrn1fm.webm", "mp3": "https://naedist.animemusicquiz.com/po87vt.mp3" },                                                                             {"id": 22, "anime": "White Album 2 Episode 2", "name": "closing '13 by Rena Uehara", "video": "https://naedist.animemusicquiz.com/3oasnn.webm", "mp3": "https://naedist.animemusicquiz.com/2gp7f4.mp3" },                                                                                                           {"id": 22, "anime": "White Album 2 Episode 2", "name": "Akujo by Madoka Yonezawa", "video": "https://naedist.animemusicquiz.com/8g1xx1.webm", "mp3": "https://naedist.animemusicquiz.com/eht0tr.mp3" }],
  [{"id": 23, "anime": "SKET Dance Episode 17", "name": "Kakko Warui I love you! by French Kiss", "video": "https://naedist.animemusicquiz.com/968nxe.webm", "mp3": "https://naedist.animemusicquiz.com/ww8irw.mp3" },                                                                         {"id": 23, "anime": "SKET Dance Episode 17", "name": "Funny Bunny (Rock Stock Version) by the pillows", "video": "https://naedist.animemusicquiz.com/5t1onl.webm", "mp3": "https://naedist.animemusicquiz.com/587vps.mp3" },                                                                                        {"id": 23, "anime": "SKET Dance Episode 17", "name": "Michi by The Sketchbook", "video": "https://naedist.animemusicquiz.com/zkysx3.webm", "mp3": "https://naedist.animemusicquiz.com/x6wxnz.mp3" }],
  [{"id": 24, "anime": "Ao no Kanata no Four Rhythm Episode 12", "name": "Contrail~Kiseki~ by Mami Kawada", "video": "https://naedist.animemusicquiz.com/v8r4gj.webm", "mp3": "https://naedist.animemusicquiz.com/reod9s.mp3" },                                                               {"id": 24, "anime": "Ao no Kanata no Four Rhythm Episode 12", "name": "Kimi to Ita Sora by Ray", "video": "https://naedist.animemusicquiz.com/lm3x74.webm", "mp3": "https://naedist.animemusicquiz.com/fa3wpa.mp3" },                                                                                               {"id": 24, "anime": "Ao no Kanata no Four Rhythm Episode 12", "name": "Wings of Courage -Sora o Koete- by Mami Kawada", "video": "https://naedist.animemusicquiz.com/rsi9jy.webm", "mp3": "https://naedist.animemusicquiz.com/x0bj5t.mp3" }],
  [{"id": 25, "anime": "Aikatsu! 10th Story: Mirai e no Starway (2023)", "name": "MY STARWAY by Waka・Fuuri・Yuna", "video": "https://naedist.animemusicquiz.com/4xovjx.webm", "mp3": "https://naedist.animemusicquiz.com/5q5ywt.mp3" },                                                        {"id": 25, "anime": "Aikatsu! 10th Story: Mirai e no Starway (2023)", "name": "Koori no Mori by Waka・Fuuri・Yuna・Remi・Eri・Risuko", "video": "https://naedist.animemusicquiz.com/im2fok.webm", "mp3": "https://naedist.animemusicquiz.com/v9nq9i.mp3" },                                                           {"id": 25, "anime": "Aikatsu! 10th Story: Mirai e no Starway (2023)", "name": "Hoshizora no Floor by Waka・Ruka", "video": "https://naedist.animemusicquiz.com/nqjxt6.webm", "mp3": "https://naedist.animemusicquiz.com/k7wi15.mp3" }],
  [{"id": 26, "anime": "MM! Episode 9", "name": "HELP!! -Heaven side- by Ayana Taketatsu & Saori Hayami", "video": "https://naedist.animemusicquiz.com/7pqeaa.webm", "mp3": "https://naedist.animemusicquiz.com/vcn3wu.mp3" },                                                                 {"id": 26, "anime": "MM! Episode 9", "name": "More-more LOVERS!! by Natsuko Aso", "video": "https://naedist.animemusicquiz.com/v6emjg.webm", "mp3": "https://naedist.animemusicquiz.com/4lfz0d.mp3" },                                                                                                              {"id": 26, "anime": "MM! Episode 9", "name": "Hallelujah♡Study by Ayana Taketatsu & Saori Hayami", "video": "https://naedist.animemusicquiz.com/ld1v24.webm", "mp3": "https://naedist.animemusicquiz.com/0fgevg.mp3" }],
  [{"id": 27, "anime": "Sakura Quest Episode 7", "name": "Morning Glory by (K)NoW_NAME:NIKIIE", "video": "https://naedist.animemusicquiz.com/rr0rdm.webm", "mp3": "https://naedist.animemusicquiz.com/da4lgq.mp3" },                                                                           {"id": 27, "anime": "Sakura Quest Episode 7", "name": "Freesia by (K)NoW_NAME:Ayaka Tachibana", "video": "https://naedist.animemusicquiz.com/tgqssv.webm", "mp3": "https://naedist.animemusicquiz.com/g2x4ni.mp3" },                                                                                                {"id": 27, "anime": "Sakura Quest Episode 7", "name": "thyme by (K)NoW_NAME:NIKIIE", "video": "https://naedist.animemusicquiz.com/2fm1wi.webm", "mp3": "https://naedist.animemusicquiz.com/zlywwn.mp3" }],
  [{"id": 28, "anime": "Macross Delta Episode 18", "name": "Zettai Reido θ Novatic by Walküre", "video": "https://naedist.animemusicquiz.com/p91l58.webm", "mp3": "https://naedist.animemusicquiz.com/t2m8p4.mp3" },                                                                           {"id": 28, "anime": "Macross Delta Episode 18", "name": "LOVE! THUNDER GROW by Walküre", "video": "https://naedist.animemusicquiz.com/z3j53t.webm", "mp3": "https://naedist.animemusicquiz.com/7teuqg.mp3" },                                                                                                       {"id": 28, "anime": "Macross Delta Episode 18", "name": "Hametsu no Junjou by Walküre", "video": "https://naedist.animemusicquiz.com/23d5la.webm", "mp3": "https://naedist.animemusicquiz.com/o7t4pm.mp3" }],
  [{"id": 29, "anime": "Project Sekai Movie: Kowareta Sekai to Utaenai Miku", "name": "Hajimari no Mirai by Hatsune Miku", "video": "https://files.catbox.moe/089s99.webm", "mp3": "https://files.catbox.moe/wmp5re.mp3" },                                                                    {"id": 29, "anime": "Project Sekai Movie: Kowareta Sekai to Utaenai Miku", "name": "Worlders by Leo/need, MORE MORE JUMP!, Vivid BAD SQUAD, WonderslandxShowtime, 25-ji, Nightcord de. & VIRTUAL SINGERS", "video": "https://files.catbox.moe/s22v91.webm", "mp3": "https://files.catbox.moe/m56jiu.mp3" },         {"id": 29, "anime": "Project Sekai Movie: Kowareta Sekai to Utaenai Miku", "name": "Soko ni Aru, Hikari by 25-ji, Nightcord de.", "video": "https://files.catbox.moe/o11ys5.webm", "mp3": "https://files.catbox.moe/w6fooz.mp3" }],
  [{"id": 30, "anime": "Macross Frontier Episode 15", "name": "Triangler by Maaya Sakamoto", "video": "https://naedist.animemusicquiz.com/g3n4yt.webm", "mp3": "https://naedist.animemusicquiz.com/hg7d08.mp3" },                                                                              {"id": 30, "anime": "Macross Frontier Episode 15", "name": "Diamond Crevasse 50/50 by Megumi Nakajima & May'n", "video": "https://naedist.animemusicquiz.com/o77st0.webm", "mp3": "https://naedist.animemusicquiz.com/q7eytg.mp3" },                                                                                {"id": 30, "anime": "Macross Frontier Episode 15", "name": "Welcome To My Fan Club's Night! by May'n", "video": "https://naedist.animemusicquiz.com/d92vtu.webm", "mp3": "https://naedist.animemusicquiz.com/72qoqh.mp3" }],
  [{"id": 31, "anime": "Arknights: Touin Kiro Episode 2", "name": "ACHE in PULSE by MYTH & ROID", "video": "https://naedist.animemusicquiz.com/d4hcub.webm", "mp3": "https://naedist.animemusicquiz.com/y3uc3a.mp3" },                                                                         {"id": 31, "anime": "Arknights: Touin Kiro Episode 2", "name": "R.I.P. by ReoNa", "video": "https://naedist.animemusicquiz.com/ymv3d3.webm", "mp3": "https://naedist.animemusicquiz.com/dd994r.mp3" },                                                                                                              {"id": 31, "anime": "Arknights: Touin Kiro Episode 2", "name": "Lullabye by Ayahi Takagaki", "video": "https://naedist.animemusicquiz.com/ygzq43.webm", "mp3": "https://naedist.animemusicquiz.com/fjk88f.mp3" }],
  [{"id": 32, "anime": "Cardfight!! Vanguard: will+Dress Season 3 Episode 4", "name": "The last resort by GYROAXIA", "video": "https://naedist.animemusicquiz.com/uxjo29.webm", "mp3": "https://naedist.animemusicquiz.com/dcy7b7.mp3" },                                                      {"id": 32, "anime": "Cardfight!! Vanguard: will+Dress Season 3 Episode 4", "name": "BLUE BUD by Hina Aoki", "video": "https://naedist.animemusicquiz.com/1n0rup.webm", "mp3": "https://naedist.animemusicquiz.com/ikiddx.mp3" },                                                                                    {"id": 32, "anime": "Cardfight!! Vanguard: will+Dress Season 3 Episode 4", "name": "erchiglhaad by Airots", "video": "https://naedist.animemusicquiz.com/jsysgc.webm", "mp3": "https://naedist.animemusicquiz.com/xaxq2i.mp3" }],
  [{"id": 33, "anime": "Yu-Gi-Oh! 5D's Final Episode Special", "name": "Asu e no Michi ~Going my way!!~ by Masaaki Endoh", "video": "https://naedist.animemusicquiz.com/yvohii.webm", "mp3": "https://naedist.animemusicquiz.com/7wwehy.mp3" },                                                {"id": 33, "anime": "Yu-Gi-Oh! 5D's Final Episode Special", "name": "Mirai Iro by Plastic Tree", "video": "https://files.catbox.moe/wbgudc.mp4", "mp3": "https://naedist.animemusicquiz.com/jdu0ct.mp3" },                                                                                                          {"id": 33, "anime": "Yu-Gi-Oh! 5D's Final Episode Special", "name": "YAKUSOKU NO MELODY by Masaaki Endoh", "video": "https://naedist.animemusicquiz.com/ykmtfs.webm", "mp3": "https://naedist.animemusicquiz.com/wnerso.mp3" }],
  [{"id": 34, "anime": "Kusuriya no Hitorigoto Episode 24", "name": "Ambivalent by Uru", "video": "https://naedist.animemusicquiz.com/86jz91.webm", "mp3": "https://naedist.animemusicquiz.com/r6nidy.mp3" },                                                                                  {"id": 34, "anime": "Kusuriya no Hitorigoto Episode 24", "name": "Ai wa Kusuri by wacci", "video": "https://naedist.animemusicquiz.com/365auo.webm", "mp3": "https://naedist.animemusicquiz.com/02gx4q.mp3" },                                                                                                      {"id": 34, "anime": "Kusuriya no Hitorigoto Episode 24", "name": "Omoi Saku Toki by Aoiema.", "video": "https://naedist.animemusicquiz.com/0mcrh9.webm", "mp3": "https://naedist.animemusicquiz.com/elibm5.mp3" }],
  [{"id": 35, "anime": "H2O: Footprints in the Sand Episode 12", "name": "Katayoku no Icarus by Yui Sakakibara", "video": "https://naedist.animemusicquiz.com/85jfvi.webm", "mp3": "https://naedist.animemusicquiz.com/90ase8.mp3" },                                                          {"id": 35, "anime": "H2O: Footprints in the Sand Episode 12", "name": "FOOTPRINTS IN THE SAND by monet", "video": "https://naedist.animemusicquiz.com/ukyiax.webm", "mp3": "https://naedist.animemusicquiz.com/c24o75.mp3" },                                                                                       {"id": 35, "anime": "H2O: Footprints in the Sand Episode 12", "name": "life by Haruka Shimotsuki", "video": "https://naedist.animemusicquiz.com/tf82bf.webm", "mp3": "https://naedist.animemusicquiz.com/o6wxgv.mp3" }],
  [{"id": 36, "anime": "Mekakucity Actors Episode 10", "name": "daze by Jin ft. MARiA from GARNiDELiA", "video": "https://naedist.animemusicquiz.com/5j4rly.webm", "mp3": "https://naedist.animemusicquiz.com/0ih9yh.mp3" },                                                                   {"id": 36, "anime": "Mekakucity Actors Episode 10", "name": "days by Jin ft. Lia", "video": "https://naedist.animemusicquiz.com/8ur9a5.webm", "mp3": "https://naedist.animemusicquiz.com/indadm.mp3" },                                                                                                             {"id": 36, "anime": "Mekakucity Actors Episode 10", "name": "Kuusou Forest by Jin ft. Takumi Yoshida (phatmans after school)", "video": "https://naedist.animemusicquiz.com/6zoft6.webm", "mp3": "https://naedist.animemusicquiz.com/8lfd5q.mp3" }],
  [{"id": 37, "anime": "Utawarerumono: Futari no Hakuoro Episode 26", "name": "Hito Nanda by Suara", "video": "https://naedist.animemusicquiz.com/13nqxw.webm", "mp3": "https://naedist.animemusicquiz.com/zwv5k4.mp3" },                                                                      {"id": 37, "anime": "Utawarerumono: Futari no Hakuoro Episode 26", "name": "Hyakunichisou by Suara", "video": "https://naedist.animemusicquiz.com/1mjtmp.webm", "mp3": "https://naedist.animemusicquiz.com/ts9mui.mp3" },                                                                                           {"id": 37, "anime": "Utawarerumono: Futari no Hakuoro Episode 26", "name": "Kimi ga Tame 2016 by Suara", "video": "https://naedist.animemusicquiz.com/nllynv.webm", "mp3": "https://naedist.animemusicquiz.com/jxm0ux.mp3" }],
  [{"id": 38, "anime": "Koi to Senkyo to Chocolate Episode 1", "name": "Signal Graph by Annabel", "video": "https://naedist.animemusicquiz.com/ufhv9q.webm", "mp3": "https://naedist.animemusicquiz.com/dptufk.mp3" },                                                                         {"id": 38, "anime": "Koi to Senkyo to Chocolate Episode 1", "name": "Kaze no Naka no Primrose by Ceui", "video": "https://naedist.animemusicquiz.com/dvg3gd.webm", "mp3": "https://naedist.animemusicquiz.com/e7vizd.mp3" },                                                                                        {"id": 38, "anime": "Koi to Senkyo to Chocolate Episode 1", "name": "Hello Mellow by Annabel", "video": "https://naedist.animemusicquiz.com/1a3smt.webm", "mp3": "https://naedist.animemusicquiz.com/nbf9f6.mp3" }],
  [{"id": 39, "anime": "Shingeki no Kyojin: The Final Season Part 2 Episode 6", "name": "The Rumbling by SiM", "video": "https://naedist.animemusicquiz.com/sm619u.webm", "mp3": "https://naedist.animemusicquiz.com/3m39p3.mp3" },                                                            {"id": 39, "anime": "Shingeki no Kyojin: The Final Season Part 2 Episode 6", "name": "Akuma no Ko by Ai Higuchi", "video": "https://naedist.animemusicquiz.com/fwrifz.webm", "mp3": "https://naedist.animemusicquiz.com/rrr1xq.mp3" },                                                                              {"id": 39, "anime": "Shingeki no Kyojin: The Final Season Part 2 Episode 6", "name": "Barricades by yosh, Gemie, mpi", "video": "https://naedist.animemusicquiz.com/vrkjxh.webm", "mp3": "https://naedist.animemusicquiz.com/qv2kif.mp3" }],
  [{"id": 40, "anime": "Fuuka Episode 12", "name": "Climber's High! by Manami Numakura", "video": "https://naedist.animemusicquiz.com/j4x8hn.webm", "mp3": "https://naedist.animemusicquiz.com/8rdgrp.mp3" },                                                                                  {"id": 40, "anime": "Fuuka Episode 12", "name": "Fair wind by Lynn", "video": "https://naedist.animemusicquiz.com/5btkvb.webm", "mp3": "https://naedist.animemusicquiz.com/bqfl5s.mp3" },                                                                                                                           {"id": 40, "anime": "Fuuka Episode 12", "name": "for you by Lynn", "video": "https://naedist.animemusicquiz.com/lsip5g.webm", "mp3": "https://naedist.animemusicquiz.com/yv8er2.mp3" }],
  [{"id": 41, "anime": "3-gatsu no Lion Episode 8", "name": "Answer by BUMP OF CHICKEN", "video": "https://naedist.animemusicquiz.com/wcxc8n.webm", "mp3": "https://naedist.animemusicquiz.com/61kwir.mp3" },                                                                                  {"id": 41, "anime": "3-gatsu no Lion Episode 8", "name": "Fighter by BUMP OF CHICKEN", "video": "https://naedist.animemusicquiz.com/f1ye43.webm", "mp3": "https://naedist.animemusicquiz.com/cc4hhx.mp3" },                                                                                                         {"id": 41, "anime": "3-gatsu no Lion Episode 8", "name": "Nyaa Shougi Ondo by Kana Hanazawa, Ai Kayano, Misaki Kuno", "video": "https://naedist.animemusicquiz.com/gxgiax.webm", "mp3": "https://naedist.animemusicquiz.com/3kjcic.mp3" }],
  [{"id": 42, "anime": "Kakuriyo no Yadomeshi Episode 20", "name": "Utsushiyo no Yume by nano", "video": "https://naedist.animemusicquiz.com/hdzapl.webm", "mp3": "https://naedist.animemusicquiz.com/qe7sbg.mp3" },                                                                           {"id": 42, "anime": "Kakuriyo no Yadomeshi Episode 20", "name": "Shiranai Kimochi by Megumi Nakajima", "video": "https://naedist.animemusicquiz.com/9hizs7.webm", "mp3": "https://naedist.animemusicquiz.com/rhgi6j.mp3" },                                                                                         {"id": 42, "anime": "Kakuriyo no Yadomeshi Episode 20", "name": "Haru-iro by Nao Touyama", "video": "https://naedist.animemusicquiz.com/9jnm82.webm", "mp3": "https://naedist.animemusicquiz.com/lffmto.mp3" }]
]